{"components_echarts_huspeed.md":"18cac16b","components_echarts_hushapechart.md":"33c653b5","components_base_hulayouttable.md":"4d90145b","components_base_hupercentagesize.md":"20644ce1","components_animation_huborderflow.md":"ef89297a","components_echarts_huareachart.md":"11630bd5","components_fun_hunumberroll.md":"4e92c697","guild_introduce.md":"79a9dbd8","externallink_animation_blockscroll.md":"3a26377c","components_fun_huwordcloud.md":"f831c0c7","externallink_components.md":"4075d6f0","guild_quickstart.md":"e8fbf85b","index.md":"bfab7e35","components_fun_huselectpage.md":"420646d4","components_echarts_hububble.md":"830b0439","components_echarts_hupiechart.md":"e2a6087a","components_fun_huturnpage.md":"9a1efabe","components_fun_hulargescreen.md":"d469fa69","components_fun_huelectrocardiogram.md":"f95f28fd","components_fun_huvirtualselectpage.md":"f87b2432","components_echarts_hulinechart.md":"a1ede47f","components_echarts_hubasechart.md":"87592e73","components_animation_huborderflowsvg.md":"b0746899","components_fun_huvirtualselect.md":"17e35315"}
